abs2rel.py
abs2rel-1.1.0.dist-info/METADATA
abs2rel-1.1.0.dist-info/WHEEL
abs2rel-1.1.0.dist-info/entry_points.txt
abs2rel-1.1.0.dist-info/top_level.txt
abs2rel-1.1.0.dist-info/RECORD
