Metadata-Version: 2.1
Name: abs2rel
Version: 1.1.0
Summary: A python script that traverses a whole package turning local absolute imports into relative ones.
Home-page: https://github.com/KennedyRichard/abs2rel
Author: Kennedy Richard
Author-email: kennedy@kennedyrichard.com
License: Unlicense
Project-URL: Source, https://github.com/KennedyRichard/abs2rel
Project-URL: Bug Tracker, https://github.com/KennedyRichard/abs2rel/issues
Keywords: parsing,imports,text,python,code,substitution,replacement,script,package
Classifier: License :: OSI Approved :: The Unlicense (Unlicense)
Classifier: Development Status :: 4 - Beta
Classifier: Programming Language :: Python :: 3
Classifier: Programming Language :: Python :: 3.6
Classifier: Programming Language :: Python :: 3.7
Classifier: Programming Language :: Python :: 3.8
Classifier: Programming Language :: Python :: 3.9
Classifier: Programming Language :: Python :: 3.10
Classifier: Programming Language :: Python :: Implementation :: CPython
Classifier: Topic :: Software Development
Classifier: Topic :: Software Development :: Libraries :: Python Modules
Classifier: Topic :: Text Processing
Requires-Python: >=3.6
